crimson/github_app/__init__.py
crimson/github_app/getter.py
crimson/github_app/loader.py
crimson_github_app-0.1.2.dist-info/LICENSE
crimson_github_app-0.1.2.dist-info/METADATA
crimson_github_app-0.1.2.dist-info/WHEEL
crimson_github_app-0.1.2.dist-info/top_level.txt
crimson_github_app-0.1.2.dist-info/RECORD
